mcts/MCTS.py
mcts/MCTS_NN.py
mcts/MonopolyBoardMCTS.py
mcts/NN.py
mcts/Node.py
mcts/State.py
mcts/__init__.py
mcts_catherineannie13-0.0.1.dist-info/LICENSE
mcts_catherineannie13-0.0.1.dist-info/METADATA
mcts_catherineannie13-0.0.1.dist-info/WHEEL
mcts_catherineannie13-0.0.1.dist-info/top_level.txt
mcts_catherineannie13-0.0.1.dist-info/RECORD
