Metadata-Version: 2.1
Name: mcts_catherineannie13
Version: 0.0.1
Summary: A package to run MCTS for Monopoly
Author-email: Catherine Jackson <catherine@uni.minerva.edu>
Project-URL: Homepage, https://github.com/catherineannie13/Capstone-Optimising-Monopoly-Gameplay-Strategies
Classifier: Programming Language :: Python :: 3
Classifier: License :: OSI Approved :: MIT License
Classifier: Operating System :: OS Independent
Requires-Python: >=3.8
License-File: LICENSE
